ipay/__init__.py
ipay-1.0.6.dist-info/METADATA
ipay-1.0.6.dist-info/WHEEL
ipay-1.0.6.dist-info/top_level.txt
ipay-1.0.6.dist-info/RECORD
